{
  "captured_at": "2026-01-29T22:08:26.410633",
  "url": "https://api.zsxq.com/v2/topics/2855121415454581/comments?sort=asc&count=30&with_sticky=true",
  "topic_id": "2855121415454581",
  "page_id": 0,
  "data": {
    "succeeded": true,
    "resp_data": {
      "comments": [
        {
          "comment_id": 2855422145841411,
          "create_time": "2024-08-27T09:54:54.266+0800",
          "owner": {
            "user_id": 28882258154421,
            "name": "Max_峯",
            "avatar_url": "https://images.zsxq.com/FhKkSU8CJAAx67nRH0qjE21A-vqq?imageMogr2/auto-orient/thumbnail/150x/format/jpg/blur/1x0/quality/75/ignore-error/1&e=1774972799&token=kIxbL07-8jAj8w1n4s9zv64FuZZNEATmlU_Vm6zD:s6ttUTEAfwD-cI04Qhd5_Bia0FQ=",
            "location": "湖北"
          },
          "text": "苦一苦，画面感十足",
          "likes_count": 0,
          "group_owner_liked": false,
          "topic_owner_liked": false,
          "rewards_count": 0,
          "sticky": false
        },
        {
          "comment_id": 2855422142511121,
          "create_time": "2024-08-27T10:28:15.364+0800",
          "owner": {
            "user_id": 48828442214588,
            "name": "似水流年",
            "avatar_url": "https://images.zsxq.com/Fp75hwycanSTWLKUpKVIpFMMPuyL?imageMogr2/auto-orient/thumbnail/150x/format/jpg/blur/1x0/quality/75/ignore-error/1&e=1774972799&token=kIxbL07-8jAj8w1n4s9zv64FuZZNEATmlU_Vm6zD:FFe02FFhTzNrARbnPeQ8vvsjWH0=",
            "location": "河北"
          },
          "text": "一声叹息",
          "likes_count": 0,
          "group_owner_liked": false,
          "topic_owner_liked": false,
          "rewards_count": 0,
          "sticky": false
        },
        {
          "comment_id": 5122455848244244,
          "create_time": "2024-08-27T14:52:44.627+0800",
          "owner": {
            "user_id": 48811511812258,
            "name": "扫地的",
            "avatar_url": "https://images.zsxq.com/FlRuuBRL5V_EvJOifHtkoMY7WXN6?imageMogr2/auto-orient/thumbnail/150x/format/jpg/blur/1x0/quality/75/ignore-error/1&e=1774972799&token=kIxbL07-8jAj8w1n4s9zv64FuZZNEATmlU_Vm6zD:QBEDJTHOT91qubK1ciuEQlxZ_cg=",
            "location": "湖南"
          },
          "text": "大明1566",
          "likes_count": 0,
          "group_owner_liked": false,
          "topic_owner_liked": false,
          "rewards_count": 0,
          "sticky": false
        }
      ],
      "index": ""
    }
  }
}