{
  "captured_at": "2026-05-09T08:07:21.998320",
  "url": "https://api.zsxq.com/v2/topics/45544881522488158/comments?sort=asc&count=30&with_sticky=true",
  "topic_id": "45544881522488158",
  "page_id": 0,
  "data": {
    "succeeded": true,
    "resp_data": {
      "comments": [
        {
          "comment_id": 5125812581588884,
          "create_time": "2026-05-02T16:44:19.790+0800",
          "owner": {
            "user_id": 118511218281852,
            "name": "好大一个饼",
            "avatar_url": "https://images.zsxq.com/FkTcrsxL0_T7zCCOI9S-WtaBRtTA?imageMogr2/auto-orient/thumbnail/150x/format/jpg/blur/1x0/quality/75/ignore-error/1&e=1782835199&token=q6iZ0sQtf9U7s1qz0r4yMawNq3-u2w6lbnai6y2J:18iOFVUH2F1Dp8MbgS31LiJVsd4=",
            "location": "广东"
          },
          "text": "要用提问功能啊",
          "likes_count": 0,
          "group_owner_liked": false,
          "topic_owner_liked": false,
          "rewards_count": 0,
          "sticky": false
        },
        {
          "comment_id": 5125812585545554,
          "create_time": "2026-05-02T20:29:54.421+0800",
          "owner": {
            "user_id": 28518212548821,
            "name": "王*",
            "avatar_url": "https://images.zsxq.com/FpbcsiwzmxZhz898X_u3hPCj5y0S?imageMogr2/auto-orient/thumbnail/150x/format/jpg/blur/1x0/quality/75/ignore-error/1&e=1782835199&token=q6iZ0sQtf9U7s1qz0r4yMawNq3-u2w6lbnai6y2J:T5JLQfcIRxVfJVUFWACVTVFeICM=",
            "location": "北京"
          },
          "text": "强国股票是啥？",
          "likes_count": 0,
          "group_owner_liked": false,
          "topic_owner_liked": false,
          "rewards_count": 0,
          "sticky": false,
          "replies_count": 1,
          "replied_comments": [
            {
              "comment_id": 2852185212481111,
              "parent_comment_id": 5125812585545554,
              "create_time": "2026-05-02T21:07:59.299+0800",
              "owner": {
                "user_id": 548142455514254,
                "name": "汪强",
                "avatar_url": "https://images.zsxq.com/FpTa7ju8crYDtW0UeoRLxM1J_IU-?imageMogr2/auto-orient/thumbnail/150x/format/jpg/blur/1x0/quality/75/ignore-error/1&e=1782835199&token=q6iZ0sQtf9U7s1qz0r4yMawNq3-u2w6lbnai6y2J:OQB3CHTHGKg0fpX7aKsjXSnIiRY=",
                "location": "山东"
              },
              "text": "五粮液",
              "likes_count": 0,
              "group_owner_liked": false,
              "topic_owner_liked": false,
              "rewards_count": 0,
              "sticky": false,
              "repliee": {
                "user_id": 28518212548821,
                "name": "王*",
                "avatar_url": "https://images.zsxq.com/FpbcsiwzmxZhz898X_u3hPCj5y0S?imageMogr2/auto-orient/thumbnail/150x/format/jpg/blur/1x0/quality/75/ignore-error/1&e=1782835199&token=q6iZ0sQtf9U7s1qz0r4yMawNq3-u2w6lbnai6y2J:T5JLQfcIRxVfJVUFWACVTVFeICM="
              }
            }
          ]
        },
        {
          "comment_id": 4845184512458188,
          "create_time": "2026-05-02T21:55:34.416+0800",
          "owner": {
            "user_id": 225858145221,
            "name": "彭磊Jimmy",
            "avatar_url": "https://images.zsxq.com/FuJB76NdkSGGM1FDDWY31sk-Lqd9?imageMogr2/auto-orient/thumbnail/150x/format/jpg/blur/1x0/quality/75/ignore-error/1&e=1782835199&token=q6iZ0sQtf9U7s1qz0r4yMawNq3-u2w6lbnai6y2J:5Emtm5yll7m-LfmNr7oG1g3i7UY=",
            "location": "北京"
          },
          "text": "这个没啥吧，很多a股财报扯淡得跟玩似的，五粮液也不是第一个。\n时代变了嘛，地产好的时候白酒好，那时候大家喜气洋洋的，现在地产下行白酒这类的资产都完蛋的，没必要多看一眼，骚操作也不会是最后一个",
          "likes_count": 0,
          "group_owner_liked": false,
          "topic_owner_liked": false,
          "rewards_count": 0,
          "sticky": false
        },
        {
          "comment_id": 5125812422154184,
          "create_time": "2026-05-03T00:54:30.297+0800",
          "owner": {
            "user_id": 144254841842,
            "name": "许哲",
            "avatar_url": "https://images.zsxq.com/Fo1faLRzTq2JvLOpLJ7CISOP_KdV?imageMogr2/auto-orient/thumbnail/150x/format/jpg/blur/1x0/quality/75/ignore-error/1&e=1782835199&token=q6iZ0sQtf9U7s1qz0r4yMawNq3-u2w6lbnai6y2J:sXkd6g78VwbAsGJE3rVPxedevlg=",
            "location": "美国"
          },
          "text": "使用提问功能，否则Timeline会乱掉的",
          "likes_count": 1,
          "group_owner_liked": false,
          "topic_owner_liked": false,
          "rewards_count": 0,
          "sticky": false
        }
      ],
      "index": ""
    }
  }
}