{
  "captured_at": "2026-03-27T20:56:14.959978",
  "url": "https://api.zsxq.com/v2/topics/82811485524218842/comments?sort=asc&count=30&with_sticky=true",
  "topic_id": "82811485524218842",
  "page_id": 0,
  "data": {
    "succeeded": true,
    "resp_data": {
      "comments": [
        {
          "comment_id": 2852448158128411,
          "create_time": "2026-03-23T15:01:05.589+0800",
          "owner": {
            "user_id": 118511218281852,
            "name": "好大一个饼",
            "avatar_url": "https://images.zsxq.com/FkTcrsxL0_T7zCCOI9S-WtaBRtTA?imageMogr2/auto-orient/thumbnail/150x/format/jpg/blur/1x0/quality/75/ignore-error/1&e=1777564799&token=q6iZ0sQtf9U7s1qz0r4yMawNq3-u2w6lbnai6y2J:XZEe4qp-l8DPPDGmUZsLzTw5pJk=",
            "location": "广东"
          },
          "text": "感觉要准备很多很多的钱钱。",
          "likes_count": 0,
          "group_owner_liked": false,
          "topic_owner_liked": false,
          "rewards_count": 0,
          "sticky": false
        }
      ],
      "index": ""
    }
  }
}