{
  "captured_at": "2026-01-29T22:38:18.581245",
  "url": "https://api.zsxq.com/v2/topics/8855211854548222/comments?sort=asc&count=30&with_sticky=true",
  "topic_id": "8855211854548222",
  "page_id": 0,
  "data": {
    "succeeded": true,
    "resp_data": {
      "comments": [
        {
          "comment_id": 5122541844451424,
          "create_time": "2024-06-05T08:53:23.270+0800",
          "owner": {
            "user_id": 815115518148112,
            "name": "岩翳",
            "avatar_url": "https://images.zsxq.com/FqvK_YGgh34biJUpyb4mtg75pGBx?imageMogr2/auto-orient/thumbnail/150x/format/jpg/blur/1x0/quality/75/ignore-error/1&e=1774972799&token=kIxbL07-8jAj8w1n4s9zv64FuZZNEATmlU_Vm6zD:kWg_Y8XI8249W5sggM40Vhlu2ZQ=",
            "location": "浙江"
          },
          "text": "许大的格局真的好高\n惊叹",
          "likes_count": 0,
          "group_owner_liked": false,
          "topic_owner_liked": false,
          "rewards_count": 0,
          "sticky": false
        }
      ],
      "index": ""
    }
  }
}